chaosgremlin/__init__.py
chaosgremlin/actions.py
chaostoolkit_gremlin-0.3.0.dist-info/DESCRIPTION.rst
chaostoolkit_gremlin-0.3.0.dist-info/METADATA
chaostoolkit_gremlin-0.3.0.dist-info/RECORD
chaostoolkit_gremlin-0.3.0.dist-info/WHEEL
chaostoolkit_gremlin-0.3.0.dist-info/metadata.json
chaostoolkit_gremlin-0.3.0.dist-info/top_level.txt
