Metadata-Version: 2.0
Name: chaostoolkit-gremlin
Version: 0.3.0
Summary: Chaos Toolkit Gremlin, Inc. support
Home-page: http://chaostoolkit.org
Author: chaostoolkit Team
Author-email: sh@defuze.org
License: Apache License Version 2.0
Platform: UNKNOWN
Classifier: Development Status :: 2 - Pre-Alpha
Classifier: Intended Audience :: Developers
Classifier: License :: Freely Distributable
Classifier: Operating System :: OS Independent
Classifier: License :: OSI Approved :: Apache Software License
Classifier: Programming Language :: Python
Classifier: Programming Language :: Python :: 3
Classifier: Programming Language :: Python :: 3.5
Classifier: Programming Language :: Python :: 3.6
Classifier: Programming Language :: Python :: Implementation
Classifier: Programming Language :: Python :: Implementation :: CPython
Requires-Python: >=3.5.*
Requires-Dist: chaostoolkit-lib (>=0.7.0)
Requires-Dist: logzero
Requires-Dist: pycodestyle
Requires-Dist: requests
